etc/profile.d/system.sh
hasis/__init__.py
hasis/bools.py
hasis/get.py
hasis/system.py
hasis-0.4.3.dist-info/LICENSE
hasis-0.4.3.dist-info/METADATA
hasis-0.4.3.dist-info/WHEEL
hasis-0.4.3.dist-info/entry_points.txt
hasis-0.4.3.dist-info/top_level.txt
hasis-0.4.3.dist-info/RECORD
