Metadata-Version: 2.1
Name: hasis
Version: 0.4.3
Summary: UNKNOWN
License: UNKNOWN
Platform: UNKNOWN
Requires-Python: >=3.9
License-File: LICENSE
Provides-Extra: test
Requires-Dist: build ; extra == 'test'
Requires-Dist: darling ; extra == 'test'
Requires-Dist: ipython ; extra == 'test'
Requires-Dist: pytest ; extra == 'test'
